edrn/auth/VERSION.txt
edrn/auth/__init__.py
edrn/auth/apps.py
edrn/auth/defaults.py
edrn/auth/forms.py
edrn/auth/urls.py
edrn/auth/views.py
edrn/auth/migrations/__init__.py
edrn/auth/templates/admin/base_site.html
edrn/auth/templates/admin/login.html
edrn/auth/templates/edrn.auth/login.html
edrn/auth/templates/edrn.auth/personal-links.html
edrn/auth/templates/edrn.auth/portal-login.html
edrn/auth/templatetags/__init__.py
edrn/auth/templatetags/edrn_auth_tags.py
edrn_auth-2.2.1.dist-info/METADATA
edrn_auth-2.2.1.dist-info/WHEEL
edrn_auth-2.2.1.dist-info/licenses/LICENSE.md
edrn_auth-2.2.1.dist-info/licenses/NOTICE.txt
edrn_auth-2.2.1.dist-info/RECORD
