Metadata-Version: 2.4
Name: edrn.auth
Version: 2.2.1
Summary: Wagtail-based authentication and authorization for the Early Detection Research Network
Project-URL: Homepage, https://github.com/EDRN/edrn.auth
Project-URL: Issues, https://github.com/EDRN/edrn.auth/issues
Author-email: Sean Kelly <kelly@seankelly.biz>
License: Apache License
License-File: LICENSE.md
License-File: NOTICE.txt
Keywords: authentication,authorization,cancer,nci,nih,wagtail
Classifier: Development Status :: 5 - Production/Stable
Classifier: Environment :: Web Environment
Classifier: Framework :: Django :: 4
Classifier: Framework :: Wagtail :: 5
Classifier: Intended Audience :: Healthcare Industry
Classifier: Intended Audience :: Science/Research
Classifier: License :: OSI Approved :: Apache Software License
Classifier: Natural Language :: English
Classifier: Operating System :: OS Independent
Classifier: Programming Language :: Python :: 3
Classifier: Topic :: Internet :: WWW/HTTP
Classifier: Topic :: Software Development :: Libraries :: Python Modules
Requires-Python: >=3.10
Requires-Dist: django<6,>4
Requires-Dist: wagtail<8,>5
